{"frames": [

{
	"filename": "bg_bai_bien",
	"frame": {"x":1,"y":1,"w":1080,"h":990},
	"rotated": false,
	"trimmed": false,
	"spriteSourceSize": {"x":0,"y":0,"w":1080,"h":990},
	"sourceSize": {"w":1080,"h":990}
},
{
	"filename": "bien",
	"frame": {"x":1,"y":992,"w":1080,"h":362},
	"rotated": false,
	"trimmed": true,
	"spriteSourceSize": {"x":0,"y":6,"w":1080,"h":362},
	"sourceSize": {"w":1080,"h":368}
},
{
	"filename": "ca_map",
	"frame": {"x":497,"y":1355,"w":367,"h":167},
	"rotated": false,
	"trimmed": false,
	"spriteSourceSize": {"x":0,"y":0,"w":367,"h":167},
	"sourceSize": {"w":367,"h":167}
},
{
	"filename": "lau_dai_cat",
	"frame": {"x":250,"y":1355,"w":220,"h":248},
	"rotated": false,
	"trimmed": false,
	"spriteSourceSize": {"x":0,"y":0,"w":220,"h":248},
	"sourceSize": {"w":220,"h":248}
},
{
	"filename": "lau_dai_cat_be",
	"frame": {"x":865,"y":1355,"w":209,"h":89},
	"rotated": false,
	"trimmed": false,
	"spriteSourceSize": {"x":0,"y":0,"w":209,"h":89},
	"sourceSize": {"w":209,"h":89}
},
{
	"filename": "slash",
	"frame": {"x":471,"y":1355,"w":25,"h":235},
	"rotated": false,
	"trimmed": false,
	"spriteSourceSize": {"x":0,"y":0,"w":25,"h":235},
	"sourceSize": {"w":25,"h":235}
},
{
	"filename": "song_bien",
	"frame": {"x":1,"y":1355,"w":248,"h":306},
	"rotated": false,
	"trimmed": false,
	"spriteSourceSize": {"x":0,"y":0,"w":248,"h":306},
	"sourceSize": {"w":248,"h":306}
},
{
	"filename": "Square",
	"frame": {"x":250,"y":1604,"w":4,"h":4},
	"rotated": false,
	"trimmed": false,
	"spriteSourceSize": {"x":0,"y":0,"w":4,"h":4},
	"sourceSize": {"w":4,"h":4}
},
{
	"filename": "van luot",
	"frame": {"x":643,"y":1523,"w":334,"h":75},
	"rotated": false,
	"trimmed": false,
	"spriteSourceSize": {"x":0,"y":0,"w":334,"h":75},
	"sourceSize": {"w":334,"h":75}
},
{
	"filename": "xeng xuc cat_",
	"frame": {"x":497,"y":1523,"w":145,"h":116},
	"rotated": false,
	"trimmed": false,
	"spriteSourceSize": {"x":0,"y":0,"w":145,"h":116},
	"sourceSize": {"w":145,"h":116}
}],
"meta": {
	"app": "https://www.codeandweb.com/texturepacker",
	"version": "1.0",
	"image": "props.png",
	"format": "RGBA8888",
	"size": {"w":1082,"h":1662},
	"scale": "1",
	"smartupdate": "$TexturePacker:SmartUpdate:0c7cf5a3de4a6c4c981957b677769f3c:a269f18308b9c2f7f8b047b09c8cf76c:f4c39b94f5b79b4c461da96ae5609d50$"
}
}
