{"frames": [

{
	"filename": "bg",
	"frame": {"x":1,"y":1,"w":51,"h":988},
	"rotated": false,
	"trimmed": false,
	"spriteSourceSize": {"x":0,"y":0,"w":51,"h":988},
	"sourceSize": {"w":51,"h":988}
},
{
	"filename": "chau_cay",
	"frame": {"x":657,"y":1,"w":177,"h":320},
	"rotated": false,
	"trimmed": true,
	"spriteSourceSize": {"x":7,"y":7,"w":177,"h":320},
	"sourceSize": {"w":191,"h":334}
},
{
	"filename": "chau_cay1",
	"frame": {"x":608,"y":656,"w":95,"h":204},
	"rotated": false,
	"trimmed": true,
	"spriteSourceSize": {"x":7,"y":7,"w":95,"h":204},
	"sourceSize": {"w":109,"h":218}
},
{
	"filename": "chau_cay1_hot",
	"frame": {"x":499,"y":651,"w":108,"h":217},
	"rotated": false,
	"trimmed": true,
	"spriteSourceSize": {"x":1,"y":1,"w":108,"h":217},
	"sourceSize": {"w":109,"h":218}
},
{
	"filename": "chau_cay_hot",
	"frame": {"x":628,"y":322,"w":191,"h":333},
	"rotated": false,
	"trimmed": true,
	"spriteSourceSize": {"x":0,"y":1,"w":191,"h":333},
	"sourceSize": {"w":191,"h":334}
},
{
	"filename": "dinh",
	"frame": {"x":209,"y":301,"w":19,"h":19},
	"rotated": false,
	"trimmed": true,
	"spriteSourceSize": {"x":7,"y":7,"w":19,"h":19},
	"sourceSize": {"w":33,"h":33}
},
{
	"filename": "dinh_hot",
	"frame": {"x":175,"y":276,"w":33,"h":33},
	"rotated": false,
	"trimmed": false,
	"spriteSourceSize": {"x":0,"y":0,"w":33,"h":33},
	"sourceSize": {"w":33,"h":33}
},
{
	"filename": "dong_ho",
	"frame": {"x":499,"y":869,"w":102,"h":100},
	"rotated": false,
	"trimmed": false,
	"spriteSourceSize": {"x":0,"y":0,"w":102,"h":100},
	"sourceSize": {"w":102,"h":100}
},
{
	"filename": "dong_ho_rung",
	"frame": {"x":53,"y":917,"w":182,"h":63},
	"rotated": false,
	"trimmed": false,
	"spriteSourceSize": {"x":0,"y":0,"w":182,"h":63},
	"sourceSize": {"w":182,"h":63}
},
{
	"filename": "giuong_lv_35",
	"frame": {"x":53,"y":1,"w":603,"h":274},
	"rotated": false,
	"trimmed": false,
	"spriteSourceSize": {"x":0,"y":0,"w":603,"h":274},
	"sourceSize": {"w":603,"h":274}
},
{
	"filename": "lo_xo",
	"frame": {"x":704,"y":656,"w":95,"h":191},
	"rotated": false,
	"trimmed": false,
	"spriteSourceSize": {"x":0,"y":0,"w":95,"h":191},
	"sourceSize": {"w":95,"h":191}
},
{
	"filename": "Rectangle 19",
	"frame": {"x":53,"y":276,"w":121,"h":36},
	"rotated": false,
	"trimmed": false,
	"spriteSourceSize": {"x":0,"y":0,"w":121,"h":36},
	"sourceSize": {"w":121,"h":36}
},
{
	"filename": "Rectangle 20",
	"frame": {"x":209,"y":276,"w":94,"h":24},
	"rotated": false,
	"trimmed": false,
	"spriteSourceSize": {"x":0,"y":0,"w":94,"h":24},
	"sourceSize": {"w":94,"h":24}
},
{
	"filename": "sach",
	"frame": {"x":499,"y":396,"w":114,"h":106},
	"rotated": false,
	"trimmed": true,
	"spriteSourceSize": {"x":7,"y":7,"w":114,"h":106},
	"sourceSize": {"w":128,"h":120}
},
{
	"filename": "sach_hot",
	"frame": {"x":499,"y":276,"w":128,"h":119},
	"rotated": false,
	"trimmed": true,
	"spriteSourceSize": {"x":0,"y":1,"w":128,"h":119},
	"sourceSize": {"w":128,"h":120}
},
{
	"filename": "Square",
	"frame": {"x":53,"y":313,"w":4,"h":4},
	"rotated": false,
	"trimmed": false,
	"spriteSourceSize": {"x":0,"y":0,"w":4,"h":4},
	"sourceSize": {"w":4,"h":4}
},
{
	"filename": "tay_dam",
	"frame": {"x":499,"y":503,"w":112,"h":147},
	"rotated": false,
	"trimmed": false,
	"spriteSourceSize": {"x":0,"y":0,"w":112,"h":147},
	"sourceSize": {"w":112,"h":147}
},
{
	"filename": "tu",
	"frame": {"x":53,"y":322,"w":445,"h":594},
	"rotated": false,
	"trimmed": false,
	"spriteSourceSize": {"x":0,"y":0,"w":445,"h":594},
	"sourceSize": {"w":445,"h":594}
}],
"meta": {
	"app": "https://www.codeandweb.com/texturepacker",
	"version": "1.0",
	"image": "props.png",
	"format": "RGBA8888",
	"size": {"w":835,"h":990},
	"scale": "1",
	"smartupdate": "$TexturePacker:SmartUpdate:cf82f277ccbe72ff8e4bc940244cfaf3:f431da352254140f84f3dd140ed8c1c0:f4c39b94f5b79b4c461da96ae5609d50$"
}
}
